clashpy/__init__.py
clashpy/clan.py
clashpy/connect.py
clashpy/league.py
clashpy/player.py
clashpy-1.0.2.dist-info/METADATA
clashpy-1.0.2.dist-info/WHEEL
clashpy-1.0.2.dist-info/top_level.txt
clashpy-1.0.2.dist-info/RECORD
