Metadata-Version: 2.1
Name: clashpy
Version: 1.0.2
Summary: A Python package to interact with the Clash of Clans API
Home-page: https://github.com/agilarasu/clashpy
Author: Agilarasu
Author-email: s.agilarasu@outlook.com
Project-URL: Documentation, https://github.com/agilarasu/clashpy/docs
Project-URL: Bug Tracker, https://github.com/agilarasu/clashpy/issues
Keywords: clashpy,Clash of Clans,API
Classifier: Development Status :: 3 - Alpha
Classifier: Intended Audience :: Developers
Classifier: License :: OSI Approved :: MIT License
Classifier: Operating System :: OS Independent
Classifier: Programming Language :: Python :: 3
Classifier: Programming Language :: Python :: 3.6
Classifier: Programming Language :: Python :: 3.7
Classifier: Programming Language :: Python :: 3.8
Classifier: Programming Language :: Python :: 3.9
Requires-Python: >=3.6
Requires-Dist: requests
